{
  "exercises": [],
  "weights": [],
  "timetasks": [],
  "trainings": [],
  "tasks": [],
  "settings": [
    {
      "id": 0,
      "startPage": [
        {
          "name": "tasks",
          "symbol": "post_add",
          "displaytext": "You have _ pinned task/s",
          "type": "task"
        },
        {
          "name": "timetask",
          "symbol": "timer",
          "displaytext": "You have worked _ today",
          "type": "task"
        },
        {
          "name": "training",
          "symbol": "emoji_events",
          "displaytext": "Create or view your trainings",
          "type": "fitness"
        },
        {
          "name": "exercise",
          "symbol": "pool",
          "displaytext": "Create or view your exercises",
          "type": "fitness"
        },
        {
          "name": "session",
          "symbol": "fitness_center",
          "displaytext": "Your previous workout session lasts _ seconds",
          "type": "fitness"
        },
        {
          "name": "weight",
          "symbol": "point_of_sale",
          "displaytext": "Your weight is currently _ kilograms",
          "type": "fitness"
        },
        {
          "name": "settings",
          "symbol": "settings",
          "displaytext": "Change whatever you want",
          "type": "general"
        }
      ],
      "settingsMenu": [
        {
          "name": "General",
          "settings": [
            {
              "displaytext": "Show Tasks module",
              "value": true
            },
            {
              "displaytext": "Show Fitness module",
              "value": false
            }
          ]
        },
        {
          "name": "Tasks",
          "settings": [
            {
              "displaytext": "Show status color",
              "value": true
            },
            {
              "displaytext": "Show creation date",
              "value": false
            },
            {
              "displaytext": "Enable task history",
              "value": false
            },
            {
              "displaytext": "Show unpinned Tasks",
              "value": false
            }
          ]
        },
        {
          "name": "Timetasks",
          "settings": [
            {
              "displaytext": "Show total this week",
              "value": true
            },
            {
              "displaytext": "Show total today",
              "value": true
            },
            {
              "displaytext": "Show week number",
              "value": false
            },
            {
              "displaytext": "Enable timetask history",
              "value": false
            }
          ]
        },
        {
          "name": "Session",
          "settings": [
            {
              "displaytext": "Play sound",
              "value": "false"
            }
          ]
        }
      ]
    }
  ]
}
